mcp_gsuite/__init__.py
mcp_gsuite/calendar.py
mcp_gsuite/gauth.py
mcp_gsuite/gmail.py
mcp_gsuite/gslide.py
mcp_gsuite/server.py
mcp_gsuite/toolhandler.py
mcp_gsuite/tools_calendar.py
mcp_gsuite/tools_gmail.py
mcp_gsuite/tools_gslide.py
gsuite_rb-0.1.7.dist-info/METADATA
gsuite_rb-0.1.7.dist-info/WHEEL
gsuite_rb-0.1.7.dist-info/entry_points.txt
gsuite_rb-0.1.7.dist-info/licenses/LICENSE
gsuite_rb-0.1.7.dist-info/RECORD
